MAVdataflash/DataFlashDict.py
MAVdataflash/MAVdataflash.py
MAVdataflash/__init__.py
MAVdataflash/__version__.py
mavdataflash-3.0.0.dist-info/licenses/LICENSE
mavdataflash-3.0.0.dist-info/METADATA
mavdataflash-3.0.0.dist-info/WHEEL
mavdataflash-3.0.0.dist-info/top_level.txt
mavdataflash-3.0.0.dist-info/RECORD
