Metadata-Version: 2.4
Name: mavdataflash
Version: 3.0.0
Summary: Read, analyze and visualize *.bin flight data logs recorded by ArduPilot
Author: General Aeronautics
License-Expression: LGPL-3.0
Project-URL: Homepage, https://github.com/generalaeronautics/MAVdataflash
Project-URL: Repository, https://github.com/generalaeronautics/MAVdataflash
Project-URL: Issues, https://github.com/generalaeronautics/MAVdataflash/issues
Keywords: ardupilot,mavlink,flight-data,analysis,visualization
Classifier: Development Status :: 5 - Production/Stable
Classifier: Intended Audience :: Developers
Classifier: Programming Language :: Python :: 3
Classifier: Programming Language :: Python :: 3.9
Classifier: Programming Language :: Python :: 3.10
Classifier: Programming Language :: Python :: 3.11
Classifier: Programming Language :: Python :: 3.12
Classifier: Programming Language :: Python :: 3.13
Classifier: Topic :: Scientific/Engineering
Classifier: Topic :: Software Development :: Libraries :: Python Modules
Requires-Python: >=3.9
License-File: LICENSE
Requires-Dist: pymavlink>=2.4.49
Requires-Dist: polars>=1.33.1
Requires-Dist: pandas
Requires-Dist: pyarrow
Dynamic: license-file
